{
    "cage": {
        "cage_type": "Drive Test Box",
        "display_readout": false,
        "dims": {
            "x": 2.5,
            "y": 2.5
        }
    },
    "actors": [
        {
            "name": "slow_camera",
            "model": "ZED 2i",
            "objective": "blue_slow_camera"
        },
        {
            "name": "tracking_camera",
            "model": "OAK-1",
            "objective": "blue_tracking_camera"
        },
        {
            "name": "calibration_target",
            "model": "CalibrationTarget8x8",
            "objective": "idle"
        }
    ]
}