{
    "type": "follow",
    "timestamp": 1713197598.6686244,
    "init": {
        "type": "relative",
        "x": 0.7357408174336855,
        "y": -0.865006419326176,
        "theta": 115.06843965018832
    },
    "sequence": [
        {
            "timestamp": 0.001,
            "x": 0.7357408174336855,
            "y": -0.865006419326176,
            "theta": 115.06843965018832,
            "vx": 0.0,
            "vy": 0.0,
            "vtheta": 0.0
        },
        {
            "timestamp": 0.0505295524597168,
            "x": 0.7357408174336855,
            "y": -0.865006419326176,
            "theta": 115.06843965018832,
            "vx": 0.0,
            "vy": 0.0,
            "vtheta": 0.0
        },
        {
            "timestamp": 0.08404071426391602,
            "x": 0.7357408174336855,
            "y": -0.865006419326176,
            "theta": 115.06843965018832,
            "vx": 0.0,
            "vy": 0.0,
            "vtheta": 0.0
        },
        {
            "timestamp": 0.14977533912658691,
            "x": 0.7357408174336855,
            "y": -0.865006419326176,
            "theta": 115.06843965018832,
            "vx": 0.0,
            "vy": 0.0,
            "vtheta": 0.0
        },
        {
            "timestamp": 0.31343348121643066,
            "x": 0.7357408174336855,
            "y": -0.865006419326176,
            "theta": 115.06843965018832,
            "vx": 0.0,
            "vy": 0.0,
            "vtheta": 0.0
        },
        {
            "timestamp": 0.3896878490447998,
            "x": 0.7357408174336855,
            "y": -0.865006419326176,
            "theta": 115.06843965018832,
            "vx": 0.0,
            "vy": 0.0,
            "vtheta": 0.0
        },
        {
            "timestamp": 0.5092938671112061,
            "x": 0.7357408174336855,
            "y": -0.865006419326176,
            "theta": 115.06843965018832,
            "vx": 0.0,
            "vy": 0.0,
            "vtheta": 0.0
        },
        {
            "timestamp": 0.6001334915161133,
            "x": 0.7357408174336855,
            "y": -0.865006419326176,
            "theta": 115.06843965018832,
            "vx": 0.0,
            "vy": 0.0,
            "vtheta": 0.0
        },
        {
            "timestamp": 0.7144618759155273,
            "x": 0.7357408174336855,
            "y": -0.865006419326176,
            "theta": 115.06843965018832,
            "vx": 0.0,
            "vy": 0.0,
            "vtheta": 0.0
        },
        {
            "timestamp": 0.7850204238891602,
            "x": 0.7357408174336855,
            "y": -0.865006419326176,
            "theta": 115.06843965018832,
            "vx": 0.0,
            "vy": 0.0,
            "vtheta": 0.0
        },
        {
            "timestamp": 0.8585780391693115,
            "x": 0.7259474812870857,
            "y": -0.8646929480599425,
            "theta": 114.71894695767574,
            "vx": -0.13313830402604598,
            "vy": 0.004261574617931853,
            "vtheta": -4.75127818080435
        },
        {
            "timestamp": 0.9338145980834961,
            "x": 0.7137003972382947,
            "y": -0.8390823165767408,
            "theta": 107.2585289489597,
            "vx": -0.1627810232889594,
            "vy": 0.34040141990562506,
            "vtheta": -99.15947933271988
        },
        {
            "timestamp": 1.0094447860717772,
            "x": 0.6963901857668265,
            "y": -0.8087781488707204,
            "theta": 106.74180046795726,
            "vx": -0.22887965681310182,
            "vy": 0.4006887793365794,
            "vtheta": -6.832304596181859
        },
        {
            "timestamp": 1.0851915607452391,
            "x": 0.6827240947253507,
            "y": -0.7852499834783413,
            "theta": 108.90003169756702,
            "vx": -0.180418124737182,
            "vy": 0.3106160690512183,
            "vtheta": 28.492714559975795
        },
        {
            "timestamp": 1.1538906822204589,
            "x": 0.6648048532329957,
            "y": -0.7443901848200815,
            "theta": 108.57596156639667,
            "vx": -0.26083654503236436,
            "vy": 0.5947645003436945,
            "vtheta": -4.717238360715269
        },
        {
            "timestamp": 1.2289648780822753,
            "x": 0.6499220546685919,
            "y": -0.7157769804968471,
            "theta": 109.17158223758658,
            "vx": -0.19824119850444297,
            "vy": 0.38113234507234106,
            "vtheta": 7.933760253472727
        },
        {
            "timestamp": 1.3039499053955077,
            "x": 0.6267427358406935,
            "y": -0.6773705015849867,
            "theta": 110.80923185346839,
            "vx": -0.3091192956571474,
            "vy": 0.5121886366917805,
            "vtheta": 21.839688195896954
        },
        {
            "timestamp": 1.3918383846282958,
            "x": 0.6024150514573542,
            "y": -0.6424806971682382,
            "theta": 128.41450215421634,
            "vx": -0.2768017446166428,
            "vy": 0.39697813321284936,
            "vtheta": 200.31374367187868
        },
        {
            "timestamp": 1.5222807655334472,
            "x": 0.5596085357247093,
            "y": -0.5637948007607632,
            "theta": 116.2413399052895,
            "vx": -0.3281641705372647,
            "vy": 0.6032233991856523,
            "vtheta": -93.32214089053097
        },
        {
            "timestamp": 1.6574061641693114,
            "x": 0.5142394270836762,
            "y": -0.508735262590436,
            "theta": 115.01424911478205,
            "vx": -0.33575559516604025,
            "vy": 0.4074699407081975,
            "vtheta": -9.081126145753021
        },
        {
            "timestamp": 1.7191830406188964,
            "x": 0.4794140765117035,
            "y": -0.4467579891304274,
            "theta": 109.05746648462812,
            "vx": -0.5637279282061645,
            "vy": 1.0032438838274247,
            "vtheta": -96.42414722950829
        },
        {
            "timestamp": 1.7999509105682372,
            "x": 0.4669358043642569,
            "y": -0.42829176768957666,
            "theta": 125.51554325314066,
            "vx": -0.1544954962322664,
            "vy": 0.2286332603847684,
            "vtheta": 203.77009792180192
        },
        {
            "timestamp": 2.519317461013794,
            "x": 0.4382364553450026,
            "y": -0.37485208036230483,
            "theta": 106.70050138662128,
            "vx": -0.03989530650470012,
            "vy": 0.07428714511979005,
            "vtheta": -26.15501353915586
        },
        {
            "timestamp": 2.6101248989105224,
            "x": 0.4084464108897784,
            "y": -0.29761098447168016,
            "theta": 107.0580152420843,
            "vx": -0.3280573171671595,
            "vy": 0.8506031849336805,
            "vtheta": 3.9370547583293454
        },
        {
            "timestamp": 2.7073817977905272,
            "x": 0.3882163874538821,
            "y": -0.25338954329501223,
            "theta": 110.83850716996669,
            "vx": -0.2080060506643957,
            "vy": 0.4546869341498143,
            "vtheta": 38.87119547731774
        },
        {
            "timestamp": 2.8169644603729247,
            "x": 0.375180550128863,
            "y": -0.21326603980634773,
            "theta": 110.95651658470736,
            "vx": -0.11895893946925411,
            "vy": 0.3661482806050165,
            "vtheta": 1.0768985892447673
        },
        {
            "timestamp": 2.9148734340667724,
            "x": 0.3466495137480459,
            "y": -0.1307032702727874,
            "theta": 102.51429012827595,
            "vx": -0.2914036916578349,
            "vy": 0.8432604940965526,
            "vtheta": -86.22525737864926
        },
        {
            "timestamp": 3.0043793449401854,
            "x": 0.3271701540327155,
            "y": -0.06996493234094202,
            "theta": 99.6401764509687,
            "vx": -0.21763210412862913,
            "vy": 0.678595830589856,
            "vtheta": -32.11088127321633
        },
        {
            "timestamp": 3.1237314472198485,
            "x": 0.3233429311728753,
            "y": -0.04308433417812963,
            "theta": 96.35775933873636,
            "vx": -0.03206665644541646,
            "vy": 0.22522098605206292,
            "vtheta": -27.50196309522101
        },
        {
            "timestamp": 3.2318361530303954,
            "x": 0.3172606549616001,
            "y": 0.01241949675764127,
            "theta": 92.43162763221365,
            "vx": -0.056262825615883784,
            "vy": 0.5134265943338413,
            "vtheta": -36.31786125391473
        },
        {
            "timestamp": 3.3230088481903075,
            "x": 0.3091386138118041,
            "y": 0.112182558382253,
            "theta": 85.48452157420816,
            "vx": -0.08908414010960629,
            "vy": 1.094220824004737,
            "vtheta": -76.19722161136764
        },
        {
            "timestamp": 3.4752448329925536,
            "x": 0.31311745108098393,
            "y": 0.13803985424456244,
            "theta": 73.0014056189074,
            "vx": 0.026135984040490497,
            "vy": 0.1698500909354511,
            "vtheta": -81.9984576676551
        },
        {
            "timestamp": 3.5969157943725585,
            "x": 0.3089097378547149,
            "y": 0.1654713728197176,
            "theta": 41.574342523413,
            "vx": -0.034582723589463564,
            "vy": 0.22545657783931336,
            "vtheta": -258.29551060536824
        },
        {
            "timestamp": 3.7189937362670897,
            "x": 0.29663718966483893,
            "y": 0.16849594886237773,
            "theta": 0.6489874962458331,
            "vx": -0.10053043161948796,
            "vy": 0.0247757784553183,
            "vtheta": -335.2395559103091
        },
        {
            "timestamp": 3.827338768005371,
            "x": 0.2558339653999595,
            "y": 0.17453300083563802,
            "theta": -36.233520330340646,
            "vx": -0.3766044793216165,
            "vy": 0.05572061659313944,
            "vtheta": -340.41715835830877
        },
        {
            "timestamp": 3.9619603881835936,
            "x": 0.2165811072161598,
            "y": 0.22586602312820186,
            "theta": -78.82193415709438,
            "vx": -0.29157915446147276,
            "vy": 0.3813133598050979,
            "vtheta": -316.3564200933836
        },
        {
            "timestamp": 4.083147836685181,
            "x": 0.2048745317351587,
            "y": 0.23291449744319045,
            "theta": -105.76089936329792,
            "vx": -0.09659891041313375,
            "vy": 0.05816175191522632,
            "vtheta": -222.2917103981333
        },
        {
            "timestamp": 4.289267850875855,
            "x": 0.18960046013579868,
            "y": 0.2166781711955865,
            "theta": -106.42475113739492,
            "vx": -0.07410280684936577,
            "vy": -0.07877122612937698,
            "vtheta": -3.2207050669174375
        },
        {
            "timestamp": 4.378085208892823,
            "x": 0.18398574433966544,
            "y": 0.2031114308568126,
            "theta": -107.80877422259623,
            "vx": -0.06321642437349458,
            "vy": -0.1527487491373261,
            "vtheta": -15.582799534938891
        },
        {
            "timestamp": 4.494923425674439,
            "x": 0.17629931507845112,
            "y": 0.16764017668694706,
            "theta": -85.34374892530649,
            "vx": -0.0657869443144714,
            "vy": -0.30359290946869993,
            "vtheta": 192.27463338711686
        },
        {
            "timestamp": 4.624016119003296,
            "x": 0.17701340460912868,
            "y": 0.15345239357974597,
            "theta": -68.4335342445275,
            "vx": 0.005531603007603613,
            "vy": -0.10990384305530287,
            "vtheta": 130.99281024140564
        },
        {
            "timestamp": 4.758894277572632,
            "x": 0.17999961740391107,
            "y": 0.13866105561027334,
            "theta": -46.084777256222345,
            "vx": 0.02214007684014526,
            "vy": -0.10966444179224868,
            "vtheta": 165.69589342974658
        },
        {
            "timestamp": 4.859075618743897,
            "x": 0.1944338578880793,
            "y": 0.13117147149840128,
            "theta": -17.633252600510154,
            "vx": 0.14408112643942564,
            "vy": -0.07476026996951728,
            "vtheta": 284.000237200588
        },
        {
            "timestamp": 5.019467426300049,
            "x": 0.19831309697219612,
            "y": 0.13311664419907396,
            "theta": -3.4105294484634343,
            "vx": 0.024186017622868483,
            "vy": 0.012127631269394396,
            "vtheta": 88.67487291748002
        },
        {
            "timestamp": 5.137695146560669,
            "x": 0.19352965485765947,
            "y": 0.1356039528901905,
            "theta": -28.41690236964686,
            "vx": -0.04045956484648507,
            "vy": 0.021038286838598815,
            "vtheta": -211.51023521437781
        },
        {
            "timestamp": 5.262590480804444,
            "x": 0.18452391181324662,
            "y": 0.13763879437910398,
            "theta": -41.583705351447016,
            "vx": -0.07210632085611116,
            "vy": 0.01629237394042127,
            "vtheta": -105.42269702486084
        },
        {
            "timestamp": 5.406016660690308,
            "x": 0.17665698736200186,
            "y": 0.13374153036671735,
            "theta": -88.35840881942428,
            "vx": -0.05484998943362436,
            "vy": -0.027172612527838345,
            "vtheta": -326.1238882970993
        },
        {
            "timestamp": 5.516095233917237,
            "x": 0.16601940166101561,
            "y": 0.11029550032286313,
            "theta": -116.77807022892802,
            "vx": -0.09663629704807943,
            "vy": -0.21299358591358064,
            "vtheta": -258.1761425170015
        },
        {
            "timestamp": 5.6333597431182865,
            "x": 0.1445914415566205,
            "y": 0.0944358088672455,
            "theta": -148.2995020309202,
            "vx": -0.18273184487266242,
            "vy": -0.13524715673713536,
            "vtheta": -268.8062399847573
        },
        {
            "timestamp": 5.734097553253174,
            "x": 0.11722751605863324,
            "y": 0.08225406757397126,
            "theta": -165.2238806775204,
            "vx": -0.2716351036551918,
            "vy": -0.12092521444493294,
            "vtheta": -168.00423419904118
        },
        {
            "timestamp": 5.839035106658936,
            "x": 0.09657711528639759,
            "y": 0.08038795454724786,
            "theta": 177.49263877574813,
            "vx": -0.19678751888169918,
            "vy": -0.017783081138815104,
            "vtheta": 3265.909184370705
        },
        {
            "timestamp": 5.937396598815918,
            "x": 0.06117725354643545,
            "y": 0.0782675472752049,
            "theta": 127.1390334596377,
            "vx": -0.35989553395006313,
            "vy": -0.021557290617946773,
            "vtheta": -511.92396751919307
        },
        {
            "timestamp": 6.029190612792969,
            "x": 0.052202333984934395,
            "y": 0.08771701211722319,
            "theta": 124.31634936901347,
            "vx": -0.0977723837607195,
            "vy": 0.1029420594286326,
            "vtheta": -30.750197843292145
        },
        {
            "timestamp": 6.164587331771851,
            "x": 0.035313470170134864,
            "y": 0.10031928201468954,
            "theta": 101.99094725104086,
            "vx": -0.12473613793724003,
            "vy": 0.09307662691170498,
            "vtheta": -164.88879705759155
        },
        {
            "timestamp": 6.265482975006104,
            "x": 0.029676645465910867,
            "y": 0.11832610273398526,
            "theta": 84.24255612797515,
            "vx": -0.055867870242293664,
            "vy": 0.17846975490793654,
            "vtheta": -175.90839955159072
        },
        {
            "timestamp": 6.380530429840088,
            "x": 0.0328064635348138,
            "y": 0.155488932365214,
            "theta": 68.48064904626966,
            "vx": 0.027204583303640374,
            "vy": 0.32302174511253107,
            "vtheta": -137.00352697458814
        },
        {
            "timestamp": 6.498231960296631,
            "x": 0.038915923374794915,
            "y": 0.18828433246939494,
            "theta": 64.40327832953326,
            "vx": 0.05190637552700994,
            "vy": 0.2786318918451911,
            "vtheta": -34.64161171839493
        },
        {
            "timestamp": 6.586976600646973,
            "x": 0.048464522869194025,
            "y": 0.2137801434321366,
            "theta": 67.63298393416876,
            "vx": 0.10759635124671879,
            "vy": 0.2872940930527246,
            "vtheta": 36.39324686973121
        },
        {
            "timestamp": 6.694676471710205,
            "x": 0.07030588512661634,
            "y": 0.28199556528849795,
            "theta": 65.12467391003524,
            "vx": 0.2027984067371713,
            "vy": 0.6333844338245392,
            "vtheta": -23.289814550110744
        },
        {
            "timestamp": 6.802769733428955,
            "x": 0.08882859173387947,
            "y": 0.324796703642639,
            "theta": 60.16889564274573,
            "vx": 0.17135856863545967,
            "vy": 0.395964907280772,
            "vtheta": -45.847245133411256
        },
        {
            "timestamp": 6.911446405410767,
            "x": 0.10471136768563155,
            "y": 0.3653816387576732,
            "theta": 55.65857207599561,
            "vx": 0.1461470586291994,
            "vy": 0.3734466134721775,
            "vtheta": -41.50222383976743
        },
        {
            "timestamp": 7.058368040084839,
            "x": 0.1189139079170255,
            "y": 0.3896444227556284,
            "theta": 52.52221028322061,
            "vx": 0.0966674531147203,
            "vy": 0.16514098860783302,
            "vtheta": -21.347174633148036
        },
        {
            "timestamp": 7.169856859207154,
            "x": 0.1522260806705473,
            "y": 0.4370054089966889,
            "theta": 45.451823828437405,
            "vx": 0.2987938433267913,
            "vy": 0.42480480656181974,
            "vtheta": -63.41789706307929
        },
        {
            "timestamp": 7.317381454467774,
            "x": 0.17658727393375193,
            "y": 0.46177394531609955,
            "theta": 29.280812205386262,
            "vx": 0.1651330967569687,
            "vy": 0.16789428417447302,
            "vtheta": -109.61569895842173
        },
        {
            "timestamp": 7.431529117584229,
            "x": 0.19592953163923427,
            "y": 0.47895217585447974,
            "theta": 0.9040290942766153,
            "vx": 0.16944944099073753,
            "vy": 0.15049130283862855,
            "vtheta": -248.5971445789411
        },
        {
            "timestamp": 7.544899774551392,
            "x": 0.19182212375063587,
            "y": 0.4803773422103831,
            "theta": -10.388005667218696,
            "vx": -0.03622990285562229,
            "vy": 0.012570857345531023,
            "vtheta": -99.60279902731762
        },
        {
            "timestamp": 7.631726099014283,
            "x": 0.19592953163923427,
            "y": 0.47895217585447974,
            "theta": 5.548230996338157,
            "vx": 0.04730602054166065,
            "vy": -0.016413989244845356,
            "vtheta": 183.54153261857772
        },
        {
            "timestamp": 7.755717350006104,
            "x": 0.20820089071572812,
            "y": 0.36843490907339976,
            "theta": -141.8769572949574,
            "vx": 0.09896955614475808,
            "vy": -0.8913311697159174,
            "vtheta": -1188.996700267344
        },
        {
            "timestamp": 7.868748022079468,
            "x": 0.22771676182794487,
            "y": 0.24013939513588528,
            "theta": -85.08386342473548,
            "vx": 0.17265995817090854,
            "vy": -1.1350504388246259,
            "vtheta": 502.4573669115186
        },
        {
            "timestamp": 7.95979340171814,
            "x": 0.3095625779917013,
            "y": -0.036362767157328356,
            "theta": -146.50021850429417,
            "vx": 0.8989562840923351,
            "vy": -3.0369708313651564,
            "vtheta": -674.5686087893674
        },
        {
            "timestamp": 8.051728559494018,
            "x": 0.3095625779917013,
            "y": -0.036362767157328356,
            "theta": -146.50021850429417,
            "vx": 0.0,
            "vy": 0.0,
            "vtheta": 0.0
        },
        {
            "timestamp": 8.148674322128295,
            "x": 0.3218862535248527,
            "y": -0.2631128419815634,
            "theta": 12.590401246405456,
            "vx": 0.12711927987654079,
            "vy": -2.3389374497948654,
            "vtheta": 1641.027059128519
        },
        {
            "timestamp": 8.24870951271057,
            "x": 0.332433754092913,
            "y": -0.2818119487505151,
            "theta": 7.507405996075758,
            "vx": 0.10543790146913715,
            "vy": -0.1869252875923933,
            "vtheta": -50.812071439491234
        },
        {
            "timestamp": 8.369316173553466,
            "x": 0.332433754092913,
            "y": -0.2818119487505151,
            "theta": 7.507405996075758,
            "vx": 0.0,
            "vy": 0.0,
            "vtheta": 0.0
        },
        {
            "timestamp": 8.47298748588562,
            "x": 0.332433754092913,
            "y": -0.2818119487505151,
            "theta": 7.507405996075758,
            "vx": 0.0,
            "vy": 0.0,
            "vtheta": 0.0
        },
        {
            "timestamp": 8.602524114608764,
            "x": 0.332433754092913,
            "y": -0.2818119487505151,
            "theta": 7.507405996075758,
            "vx": 0.0,
            "vy": 0.0,
            "vtheta": 0.0
        },
        {
            "timestamp": 8.692039323806762,
            "x": 0.332433754092913,
            "y": -0.2818119487505151,
            "theta": 7.507405996075758,
            "vx": 0.0,
            "vy": 0.0,
            "vtheta": 0.0
        },
        {
            "timestamp": 8.812702966690063,
            "x": 0.332433754092913,
            "y": -0.2818119487505151,
            "theta": 7.507405996075758,
            "vx": 0.0,
            "vy": 0.0,
            "vtheta": 0.0
        },
        {
            "timestamp": 8.94350726699829,
            "x": 0.332433754092913,
            "y": -0.2818119487505151,
            "theta": 7.507405996075758,
            "vx": 0.0,
            "vy": 0.0,
            "vtheta": 0.0
        },
        {
            "timestamp": 9.036581111907958,
            "x": 0.332433754092913,
            "y": -0.2818119487505151,
            "theta": 7.507405996075758,
            "vx": 0.0,
            "vy": 0.0,
            "vtheta": 0.0
        },
        {
            "timestamp": 9.130183053970336,
            "x": 0.332433754092913,
            "y": -0.2818119487505151,
            "theta": 7.507405996075758,
            "vx": 0.0,
            "vy": 0.0,
            "vtheta": 0.0
        },
        {
            "timestamp": 9.224690509796142,
            "x": 0.332433754092913,
            "y": -0.2818119487505151,
            "theta": 7.507405996075758,
            "vx": 0.0,
            "vy": 0.0,
            "vtheta": 0.0
        },
        {
            "timestamp": 9.345151020050048,
            "x": 0.332433754092913,
            "y": -0.2818119487505151,
            "theta": 7.507405996075758,
            "vx": 0.0,
            "vy": 0.0,
            "vtheta": 0.0
        },
        {
            "timestamp": 9.438452793121337,
            "x": 0.332433754092913,
            "y": -0.2818119487505151,
            "theta": 7.507405996075758,
            "vx": 0.0,
            "vy": 0.0,
            "vtheta": 0.0
        },
        {
            "timestamp": 9.523309064865112,
            "x": 0.332433754092913,
            "y": -0.2818119487505151,
            "theta": 7.507405996075758,
            "vx": 0.0,
            "vy": 0.0,
            "vtheta": 0.0
        },
        {
            "timestamp": 9.652060581207275,
            "x": 0.332433754092913,
            "y": -0.2818119487505151,
            "theta": 7.507405996075758,
            "vx": 0.0,
            "vy": 0.0,
            "vtheta": 0.0
        },
        {
            "timestamp": 9.774010492324829,
            "x": 0.332433754092913,
            "y": -0.2818119487505151,
            "theta": 7.507405996075758,
            "vx": 0.0,
            "vy": 0.0,
            "vtheta": 0.0
        },
        {
            "timestamp": 9.864143444061279,
            "x": 0.3215699036881785,
            "y": -0.2825353758990777,
            "theta": 0.2177464969699474,
            "vx": -0.12053139496086294,
            "vy": -0.00802622275899623,
            "vtheta": -80.87674217550159
        },
        {
            "timestamp": 10.005714012145996,
            "x": 0.31479674982840977,
            "y": -0.2819756530655013,
            "theta": -11.67324598344508,
            "vx": -0.04784295176180709,
            "vy": 0.003953666649422621,
            "vtheta": -83.99339383380433
        },
        {
            "timestamp": 10.096517873764038,
            "x": 0.2985146733575589,
            "y": -0.2789885999310583,
            "theta": -17.892157563902675,
            "vx": -0.17931039694479,
            "vy": 0.032895661937900736,
            "vtheta": -68.48730295873175
        },
        {
            "timestamp": 10.193967176437377,
            "x": 0.29059455106503834,
            "y": -0.27339804603065815,
            "theta": -31.99392427912896,
            "vx": -0.08127428391221646,
            "vy": 0.057368844589275894,
            "vtheta": -144.70874935346504
        },
        {
            "timestamp": 10.312641931533813,
            "x": 0.27999126739505686,
            "y": -0.265913536740411,
            "theta": -39.04807967006678,
            "vx": -0.08934742406980499,
            "vy": 0.06306740876916234,
            "vtheta": -59.44107814004404
        },
        {
            "timestamp": 10.402998996734619,
            "x": 0.2832416064392942,
            "y": -0.25964253400133286,
            "theta": -53.251338953678555,
            "vx": 0.03597216263071308,
            "vy": 0.06940246150250398,
            "vtheta": -157.1903564159268
        },
        {
            "timestamp": 10.522106958389282,
            "x": 0.2779395317533289,
            "y": -0.2558899962996792,
            "theta": -58.30781194065861,
            "vx": -0.04451486376148305,
            "vy": 0.03150534732962385,
            "vtheta": -42.4528546768401
        },
        {
            "timestamp": 10.608791662216186,
            "x": 0.27228470793969856,
            "y": -0.2504601229329241,
            "theta": -64.50207353669896,
            "vx": -0.06523439042858303,
            "vy": 0.06263934843219517,
            "vtheta": -71.45737739854674
        },
        {
            "timestamp": 10.709016157150268,
            "x": 0.27126460572279504,
            "y": -0.24545949371356854,
            "theta": -73.27762577835071,
            "vx": -0.010178172686970808,
            "vy": 0.04989428205793873,
            "vtheta": -87.55895699373153
        },
        {
            "timestamp": 10.829686237335205,
            "x": 0.2768416388113496,
            "y": -0.2394758689315492,
            "theta": -81.32274498888403,
            "vx": 0.04621719882846944,
            "vy": 0.04958664793169068,
            "vtheta": -66.67037262429534
        },
        {
            "timestamp": 10.959038091659545,
            "x": 0.2721603154261985,
            "y": -0.22765623782095268,
            "theta": -90.85573869771586,
            "vx": -0.03619061674533863,
            "vy": 0.09137581499960273,
            "vtheta": -73.69816040617799
        },
        {
            "timestamp": 11.08230931854248,
            "x": 0.28043103858774593,
            "y": -0.19167528989813043,
            "theta": -131.52550061100158,
            "vx": 0.06709370362154159,
            "vy": 0.291884398595236,
            "vtheta": -329.92096324236354
        },
        {
            "timestamp": 11.180375171661376,
            "x": 0.28043103858774593,
            "y": -0.19167528989813043,
            "theta": -131.52550061100158,
            "vx": 0.0,
            "vy": 0.0,
            "vtheta": 0.0
        },
        {
            "timestamp": 11.299694133758544,
            "x": 0.3054621131358914,
            "y": -0.1648702107161539,
            "theta": -173.48186050290036,
            "vx": 0.2097828719609653,
            "vy": 0.2246506230933159,
            "vtheta": -351.631954841607
        },
        {
            "timestamp": 11.403679920196533,
            "x": 0.3158258608813811,
            "y": -0.1630811322014092,
            "theta": 177.90349650775056,
            "vx": 0.09966504173789276,
            "vy": 0.017205029418242698,
            "vtheta": 3379.1671828168446
        },
        {
            "timestamp": 11.509510589599609,
            "x": 0.34093338444231336,
            "y": -0.16167455751450205,
            "theta": 143.30323937633887,
            "vx": 0.2372424147229524,
            "vy": 0.013290804025343139,
            "vtheta": -326.9397928461555
        },
        {
            "timestamp": 11.615345788955688,
            "x": 0.34093338444231336,
            "y": -0.16167455751450205,
            "theta": 143.30323937633887,
            "vx": 0.0,
            "vy": 0.0,
            "vtheta": 0.0
        },
        {
            "timestamp": 11.750724388122558,
            "x": 0.34455556293337125,
            "y": -0.15909543372126475,
            "theta": 153.6602843193639,
            "vx": 0.026755916469434947,
            "vy": 0.019051192796419935,
            "vtheta": 76.50429984327702
        },
        {
            "timestamp": 11.845831466674804,
            "x": 0.33092292172447574,
            "y": -0.1542804806930463,
            "theta": 158.33457951274673,
            "vx": -0.14333992186929137,
            "vy": 0.05062665262684305,
            "vtheta": 49.14771081749759
        },
        {
            "timestamp": 11.97219116783142,
            "x": 0.3218816052646328,
            "y": -0.15157196760165134,
            "theta": 172.08635616072772,
            "vx": -0.07155221464663584,
            "vy": 0.021434943788272424,
            "vtheta": 108.83039863268104
        },
        {
            "timestamp": 12.078162265777587,
            "x": 0.29209404446466153,
            "y": -0.1631962433517498,
            "theta": -163.61358084891086,
            "vx": -0.28109136714902433,
            "vy": -0.1096928877343853,
            "vtheta": -3167.8442850537717
        },
        {
            "timestamp": 12.175710512161254,
            "x": 0.2819432843026088,
            "y": -0.17762134844801,
            "theta": -149.851990815433,
            "vx": -0.10405886869691934,
            "vy": -0.14787662137487165,
            "vtheta": 141.0747045041912
        },
        {
            "timestamp": 12.270381523132324,
            "x": 0.2658051225082929,
            "y": -0.20762416653125626,
            "theta": -117.42235704551678,
            "vx": -0.17046571731707355,
            "vy": -0.31691663346042503,
            "vtheta": 342.55083406499637
        },
        {
            "timestamp": 12.408581090927123,
            "x": 0.26121526350146784,
            "y": -0.21843678029791405,
            "theta": -107.27752728602727,
            "vx": -0.03321181882160545,
            "vy": -0.07823912866871245,
            "vtheta": 73.40710192779085
        },
        {
            "timestamp": 12.522288871765136,
            "x": 0.26121526350146784,
            "y": -0.21843678029791405,
            "theta": -107.27752728602727,
            "vx": 0.0,
            "vy": 0.0,
            "vtheta": 0.0
        },
        {
            "timestamp": 12.63855202293396,
            "x": 0.2664777018540873,
            "y": -0.21091558122225956,
            "theta": -120.5206543572428,
            "vx": 0.04526316635765355,
            "vy": 0.06469116826820835,
            "vtheta": -113.90648660456034
        },
        {
            "timestamp": 12.760793758392333,
            "x": 0.27399400780165956,
            "y": -0.2037025587528608,
            "theta": -131.50663941620016,
            "vx": 0.061487231994769166,
            "vy": 0.05900621782202157,
            "vtheta": -89.87098406090874
        },
        {
            "timestamp": 12.873327327728271,
            "x": 0.27399400780165956,
            "y": -0.2037025587528608,
            "theta": -131.50663941620016,
            "vx": 0.0,
            "vy": 0.0,
            "vtheta": 0.0
        },
        {
            "timestamp": 12.980816436767578,
            "x": 0.27399400780165956,
            "y": -0.2037025587528608,
            "theta": -131.50663941620016,
            "vx": 0.0,
            "vy": 0.0,
            "vtheta": 0.0
        },
        {
            "timestamp": 13.09924275970459,
            "x": 0.27399400780165956,
            "y": -0.2037025587528608,
            "theta": -131.50663941620016,
            "vx": 0.0,
            "vy": 0.0,
            "vtheta": 0.0
        },
        {
            "timestamp": 13.237767530441284,
            "x": 0.28656151391278417,
            "y": -0.18921190028438023,
            "theta": -142.1737830261678,
            "vx": 0.09072389035036,
            "vy": 0.10460698394530599,
            "vtheta": -77.00531502949443
        },
        {
            "timestamp": 13.329755855560302,
            "x": 0.2833774027767657,
            "y": -0.19518512542573443,
            "theta": -153.85833671355678,
            "vx": -0.034614296237035734,
            "vy": -0.0649346004900707,
            "vtheta": -127.02213756225035
        },
        {
            "timestamp": 13.43329079246521,
            "x": 0.2884844787310928,
            "y": -0.18785466200222772,
            "theta": -157.5309478804334,
            "vx": 0.0493270784432672,
            "vy": 0.07080183407306709,
            "vtheta": -35.4721920606351
        },
        {
            "timestamp": 13.539183689117431,
            "x": 0.28781019769131305,
            "y": -0.18462041966463824,
            "theta": -149.47154237869523,
            "vx": -0.006367575740176781,
            "vy": 0.03054258066253046,
            "vtheta": 76.10902861791783
        },
        {
            "timestamp": 13.66538889503479,
            "x": 0.27890690814922114,
            "y": -0.20583968113088913,
            "theta": -141.880380731809,
            "vx": -0.07054613537829774,
            "vy": -0.168133012517294,
            "vtheta": 60.14935431314199
        },
        {
            "timestamp": 13.772613836288452,
            "x": 0.27737075233144504,
            "y": -0.22011582931838675,
            "theta": -121.40469718028143,
            "vx": -0.014326478520907028,
            "vy": -0.13314204718214323,
            "vtheta": 190.96008178813761
        },
        {
            "timestamp": 13.883526874542236,
            "x": 0.2729014682445787,
            "y": -0.24235169236877319,
            "theta": -100.49524397263593,
            "vx": -0.04029538958837262,
            "vy": -0.20048015454691404,
            "vtheta": 188.521147169387
        },
        {
            "timestamp": 13.994599653244018,
            "x": 0.2761619920676932,
            "y": -0.2361611539531395,
            "theta": -108.564684033811,
            "vx": 0.029354841584260858,
            "vy": 0.05573407353258516,
            "vtheta": -72.65002420476578
        },
        {
            "timestamp": 14.115773273468017,
            "x": 0.2881160587385295,
            "y": -0.21802693438962045,
            "theta": -142.3555178137295,
            "vx": 0.09865238530249636,
            "vy": 0.14965484673971532,
            "vtheta": -278.8629548036402
        },
        {
            "timestamp": 14.226045919418334,
            "x": 0.30779188482079456,
            "y": -0.19637611532715715,
            "theta": -163.8119015068166,
            "vx": 0.1784288924302211,
            "vy": 0.19633898212815112,
            "vtheta": -194.57575818715856
        },
        {
            "timestamp": 14.325105024337768,
            "x": 0.3318910115744012,
            "y": -0.18823726207175534,
            "theta": 158.66760377483143,
            "vx": 0.24328027971993957,
            "vy": 0.08216158688311666,
            "vtheta": 3255.4251882643794
        },
        {
            "timestamp": 14.43737466430664,
            "x": 0.3731259791240779,
            "y": -0.19462237097348875,
            "theta": 118.18478053974371,
            "vx": 0.3672851143114873,
            "vy": -0.05687297922665245,
            "vtheta": -360.5856689868428
        },
        {
            "timestamp": 14.607251716613769,
            "x": 0.39771628514748325,
            "y": -0.24033837998395968,
            "theta": 46.14651101480933,
            "vx": 0.14475354787147673,
            "vy": -0.26911232794302764,
            "vtheta": -424.0612169011087
        },
        {
            "timestamp": 14.710317207336425,
            "x": 0.3789125392978788,
            "y": -0.277732218865492,
            "theta": -0.20410226590115713,
            "vx": -0.1824446351320861,
            "vy": -0.36281628913170494,
            "vtheta": -449.72000769333664
        },
        {
            "timestamp": 14.803561283111572,
            "x": 0.37239878970648205,
            "y": -0.2867357954818502,
            "theta": -11.733154690823202,
            "vx": -0.0698569805882828,
            "vy": -0.09655923490592457,
            "vtheta": -123.64380609792079
        },
        {
            "timestamp": 14.914261890411376,
            "x": 0.38749703146991415,
            "y": -0.27847243932647264,
            "theta": 3.931618389002495,
            "vx": 0.1363880662600371,
            "vy": 0.07464598755992663,
            "vtheta": 141.50575558634117
        },
        {
            "timestamp": 15.046200824737548,
            "x": 0.39674021478255617,
            "y": -0.2824239363783918,
            "theta": 11.782031982198648,
            "vx": 0.07005652546648242,
            "vy": -0.0299494388983808,
            "vtheta": 59.50035623138209
        },
        {
            "timestamp": 15.161187482833862,
            "x": 0.4218600321639218,
            "y": -0.2658841907498123,
            "theta": 32.92656270422958,
            "vx": 0.21845853942746252,
            "vy": 0.14384056291753197,
            "vtheta": 183.886818454365
        },
        {
            "timestamp": 15.282311988830566,
            "x": 0.42995624735183546,
            "y": -0.24818112154893615,
            "theta": 45.67874286158391,
            "vx": 0.0668420904695698,
            "vy": 0.14615596617052748,
            "vtheta": 105.2815865164505
        },
        {
            "timestamp": 15.394113374710082,
            "x": 0.436860987108125,
            "y": -0.2260988654885398,
            "theta": 72.6733858436438,
            "vx": 0.061758981804845035,
            "vy": 0.19751325877295847,
            "vtheta": 241.4517742306953
        },
        {
            "timestamp": 15.579650712966918,
            "x": 0.4405781674147765,
            "y": -0.1995539160396951,
            "theta": 92.76671789099724,
            "vx": 0.020034675184926385,
            "vy": 0.14307066005279762,
            "vtheta": 108.29805060337026
        },
        {
            "timestamp": 15.681569648742675,
            "x": 0.4255507885259189,
            "y": -0.17694548483903133,
            "theta": 115.84440037881426,
            "vx": -0.1474444250666141,
            "vy": 0.22182758315301776,
            "vtheta": 226.43174511351634
        },
        {
            "timestamp": 15.839814973831176,
            "x": 0.41159840163416184,
            "y": -0.16775627693464262,
            "theta": 130.37111058500736,
            "vx": -0.08816934644959633,
            "vy": 0.05806937992796635,
            "vtheta": 91.79866892161793
        },
        {
            "timestamp": 15.973136497497558,
            "x": 0.3785235134064006,
            "y": -0.15449645129220504,
            "theta": 166.61141147240622,
            "vx": -0.24808363509650871,
            "vy": 0.09945750151804751,
            "vtheta": 271.8263329939512
        },
        {
            "timestamp": 16.052844358444215,
            "x": 0.35415006246316183,
            "y": -0.16488474496890593,
            "theta": -176.08299550351882,
            "vx": -0.30578478275248466,
            "vy": -0.13032960053529788,
            "vtheta": -4299.380298327999
        },
        {
            "timestamp": 16.172532392501832,
            "x": 0.3232740003460144,
            "y": -0.17791109196230298,
            "theta": -132.40017697532875,
            "vx": -0.2579711694678172,
            "vy": -0.1088358338906815,
            "vtheta": 364.97231216247894
        },
        {
            "timestamp": 16.334052158355714,
            "x": 0.3100199967250163,
            "y": -0.1966296431576277,
            "theta": -120.48366645762809,
            "vx": -0.08205809085303081,
            "vy": -0.11589015806435966,
            "vtheta": 73.7774132763471
        },
        {
            "timestamp": 16.443031621932985,
            "x": 0.30306533956259857,
            "y": -0.2259793139077611,
            "theta": -94.51537790727357,
            "vx": -0.06381621760770192,
            "vy": -0.2693137751529065,
            "vtheta": 238.28607425601822
        },
        {
            "timestamp": 16.58463699913025,
            "x": 0.30306533956259857,
            "y": -0.2259793139077611,
            "theta": -94.51537790727357,
            "vx": 0.0,
            "vy": 0.0,
            "vtheta": 0.0
        },
        {
            "timestamp": 16.706533027648927,
            "x": 0.30306533956259857,
            "y": -0.2259793139077611,
            "theta": -94.51537790727357,
            "vx": 0.0,
            "vy": 0.0,
            "vtheta": 0.0
        },
        {
            "timestamp": 16.82849629020691,
            "x": 0.30306533956259857,
            "y": -0.2259793139077611,
            "theta": -94.51537790727357,
            "vx": 0.0,
            "vy": 0.0,
            "vtheta": 0.0
        },
        {
            "timestamp": 16.951950860977174,
            "x": 0.30306533956259857,
            "y": -0.2259793139077611,
            "theta": -94.51537790727357,
            "vx": 0.0,
            "vy": 0.0,
            "vtheta": 0.0
        },
        {
            "timestamp": 17.05309517478943,
            "x": 0.30306533956259857,
            "y": -0.2259793139077611,
            "theta": -94.51537790727357,
            "vx": 0.0,
            "vy": 0.0,
            "vtheta": 0.0
        },
        {
            "timestamp": 17.21025498008728,
            "x": 0.3129031124072538,
            "y": -0.24136671760156284,
            "theta": -80.80984478023332,
            "vx": 0.0625972577785431,
            "vy": -0.09790928198618788,
            "vtheta": 87.20762348276855
        },
        {
            "timestamp": 17.35064394569397,
            "x": 0.3141069710750192,
            "y": -0.2575658990977488,
            "theta": -68.5284001997093,
            "vx": 0.008575165879760835,
            "vy": -0.11538785421048846,
            "vtheta": 87.48155189725837
        },
        {
            "timestamp": 17.491977048873903,
            "x": 0.3354918712723888,
            "y": -0.2756013655298126,
            "theta": -40.693332130078005,
            "vx": 0.1513085025108687,
            "vy": -0.12760964010747586,
            "vtheta": 196.94655705814634
        },
        {
            "timestamp": 17.637723041534425,
            "x": 0.366991980236371,
            "y": -0.28149118391692407,
            "theta": -7.517998041336006,
            "vx": 0.21613018916652854,
            "vy": -0.04041152884958046,
            "vtheta": 227.62433109235013
        },
        {
            "timestamp": 17.75464923477173,
            "x": 0.397436277333615,
            "y": -0.276180626029051,
            "theta": 17.170731555716056,
            "vx": 0.26037191714141006,
            "vy": 0.04541803458096967,
            "vtheta": 211.14798073469865
        },
        {
            "timestamp": 17.87521178817749,
            "x": 0.41347436670044424,
            "y": -0.25580721666748896,
            "theta": 37.61123580777876,
            "vx": 0.13302712089094493,
            "vy": 0.16898621326469365,
            "vtheta": 169.54272843964043
        },
        {
            "timestamp": 18.028587175369264,
            "x": 0.4348277689970083,
            "y": -0.22587927002126199,
            "theta": 68.86670120393323,
            "vx": 0.1392231353904581,
            "vy": 0.1951287438890482,
            "vtheta": 203.7841010114243
        },
        {
            "timestamp": 18.159749580383302,
            "x": 0.4325042063281269,
            "y": -0.1985981159830278,
            "theta": 85.05065244137869,
            "vx": -0.01771515754558411,
            "vy": 0.20799522573037862,
            "vtheta": 123.3886435348095
        },
        {
            "timestamp": 18.291958881378175,
            "x": 0.4325042063281269,
            "y": -0.1985981159830278,
            "theta": 85.05065244137869,
            "vx": 0.0,
            "vy": 0.0,
            "vtheta": 0.0
        },
        {
            "timestamp": 18.440295291900636,
            "x": 0.4325042063281269,
            "y": -0.1985981159830278,
            "theta": 85.05065244137869,
            "vx": 0.0,
            "vy": 0.0,
            "vtheta": 0.0
        },
        {
            "timestamp": 18.54951508140564,
            "x": 0.430922755293564,
            "y": -0.2088857903946581,
            "theta": 84.76350229570504,
            "vx": -0.014479528313781005,
            "vy": -0.09419240284434799,
            "vtheta": -2.6291036356601953
        },
        {
            "timestamp": 18.656028820037843,
            "x": 0.430922755293564,
            "y": -0.2088857903946581,
            "theta": 84.76350229570504,
            "vx": 0.0,
            "vy": 0.0,
            "vtheta": 0.0
        },
        {
            "timestamp": 18.78065784072876,
            "x": 0.430922755293564,
            "y": -0.2088857903946581,
            "theta": 84.76350229570504,
            "vx": 0.0,
            "vy": 0.0,
            "vtheta": 0.0
        },
        {
            "timestamp": 18.933050943374635,
            "x": 0.42402748715540545,
            "y": -0.1960987383853139,
            "theta": 97.30539391237957,
            "vx": -0.04524658936947785,
            "vy": 0.08390833828653213,
            "vtheta": 82.29960148405772
        },
        {
            "timestamp": 19.034618927001954,
            "x": 0.42563055325422344,
            "y": -0.1858556720992774,
            "theta": 110.34121359230853,
            "vx": 0.015783183258811978,
            "vy": 0.1008493613855829,
            "vtheta": 128.34575635331055
        },
        {
            "timestamp": 19.152621580123903,
            "x": 0.42121434941148383,
            "y": -0.1838240897626809,
            "theta": 115.57265116377407,
            "vx": -0.03742461483620831,
            "vy": 0.01721641236741511,
            "vtheta": 44.333219915480846
        },
        {
            "timestamp": 19.287436796188356,
            "x": 0.4194615567253731,
            "y": -0.17617607665816248,
            "theta": 111.46612201280257,
            "vx": -0.01300144551393029,
            "vy": 0.056729598689082714,
            "vtheta": -30.460427768095755
        },
        {
            "timestamp": 19.40543015098572,
            "x": 0.4194615567253731,
            "y": -0.17617607665816248,
            "theta": 111.46612201280257,
            "vx": 0.0,
            "vy": 0.0,
            "vtheta": 0.0
        },
        {
            "timestamp": 19.566834999084474,
            "x": 0.4194615567253731,
            "y": -0.17617607665816248,
            "theta": 111.46612201280257,
            "vx": 0.0,
            "vy": 0.0,
            "vtheta": 0.0
        },
        {
            "timestamp": 19.741443229675294,
            "x": 0.4071580112765068,
            "y": -0.16569819253480098,
            "theta": 130.14334994491446,
            "vx": -0.0704637198786959,
            "vy": 0.060007962327477835,
            "vtheta": 106.96648072610277
        },
        {
            "timestamp": 19.84375507926941,
            "x": 0.3809566180652947,
            "y": -0.15631270592635124,
            "theta": 154.14708942691374,
            "vx": -0.2560934370276395,
            "vy": 0.0917341114023754,
            "vtheta": 234.61348394369847
        },
        {
            "timestamp": 19.975369049072267,
            "x": 0.35882645121182055,
            "y": -0.15791664712404213,
            "theta": 179.93513853913376,
            "vx": -0.16814451297702468,
            "vy": -0.01218670935990625,
            "vtheta": 195.9370205977963
        },
        {
            "timestamp": 20.074497772216798,
            "x": 0.3296350999787202,
            "y": -0.16789718432544964,
            "theta": -160.03227641201372,
            "vx": -0.29447924180904556,
            "vy": -0.1006825961720069,
            "vtheta": -3429.5550690738705
        },
        {
            "timestamp": 20.202057434082032,
            "x": 0.31054256383633827,
            "y": -0.18884979043888886,
            "theta": -130.45043747743802,
            "vx": -0.14967534299795357,
            "vy": -0.16425730365744817,
            "vtheta": 231.90590584842286
        },
        {
            "timestamp": 20.37031872367859,
            "x": 0.297653874953732,
            "y": -0.23183639621068974,
            "theta": -86.05348824584323,
            "vx": -0.07659925175606125,
            "vy": -0.25547531386969907,
            "vtheta": 263.85717914112007
        },
        {
            "timestamp": 20.48171026802063,
            "x": 0.3080258800666537,
            "y": -0.2602472156405751,
            "theta": -57.23928048299277,
            "vx": 0.09311303810523724,
            "vy": -0.255053645208891,
            "vtheta": 258.67500027087334
        },
        {
            "timestamp": 20.602747512817384,
            "x": 0.32536815737387415,
            "y": -0.27959962973972513,
            "theta": -51.60227996648191,
            "vx": 0.14328050292570502,
            "vy": -0.1598880917328116,
            "vtheta": 46.57244574574192
        },
        {
            "timestamp": 20.74922783470154,
            "x": 0.3298489310462169,
            "y": -0.2799752828336726,
            "theta": -44.61542812660082,
            "vx": 0.03058959466163908,
            "vy": -0.0025645294133404446,
            "vtheta": 47.698228335452995
        },
        {
            "timestamp": 20.87078602409363,
            "x": 0.3298489310462169,
            "y": -0.2799752828336726,
            "theta": -44.61542812660082,
            "vx": 0.0,
            "vy": 0.0,
            "vtheta": 0.0
        },
        {
            "timestamp": 20.972278667449952,
            "x": 0.3298489310462169,
            "y": -0.2799752828336726,
            "theta": -44.61542812660082,
            "vx": 0.0,
            "vy": 0.0,
            "vtheta": 0.0
        },
        {
            "timestamp": 21.091615510940553,
            "x": 0.3298489310462169,
            "y": -0.2799752828336726,
            "theta": -44.61542812660082,
            "vx": 0.0,
            "vy": 0.0,
            "vtheta": 0.0
        },
        {
            "timestamp": 21.196241928100587,
            "x": 0.3298489310462169,
            "y": -0.2799752828336726,
            "theta": -44.61542812660082,
            "vx": 0.0,
            "vy": 0.0,
            "vtheta": 0.0
        },
        {
            "timestamp": 21.289201570510865,
            "x": 0.3298489310462169,
            "y": -0.2799752828336726,
            "theta": -44.61542812660082,
            "vx": 0.0,
            "vy": 0.0,
            "vtheta": 0.0
        },
        {
            "timestamp": 21.435778451919557,
            "x": 0.3298489310462169,
            "y": -0.2799752828336726,
            "theta": -44.61542812660082,
            "vx": 0.0,
            "vy": 0.0,
            "vtheta": 0.0
        },
        {
            "timestamp": 21.549312425613405,
            "x": 0.3298489310462169,
            "y": -0.2799752828336726,
            "theta": -44.61542812660082,
            "vx": 0.0,
            "vy": 0.0,
            "vtheta": 0.0
        },
        {
            "timestamp": 21.661638332366945,
            "x": 0.3298489310462169,
            "y": -0.2799752828336726,
            "theta": -44.61542812660082,
            "vx": 0.0,
            "vy": 0.0,
            "vtheta": 0.0
        },
        {
            "timestamp": 21.783686471939088,
            "x": 0.3298489310462169,
            "y": -0.2799752828336726,
            "theta": -44.61542812660082,
            "vx": 0.0,
            "vy": 0.0,
            "vtheta": 0.0
        },
        {
            "timestamp": 21.89752156829834,
            "x": 0.3298489310462169,
            "y": -0.2799752828336726,
            "theta": -44.61542812660082,
            "vx": 0.0,
            "vy": 0.0,
            "vtheta": 0.0
        },
        {
            "timestamp": 21.986412120819093,
            "x": 0.3298489310462169,
            "y": -0.2799752828336726,
            "theta": -44.61542812660082,
            "vx": 0.0,
            "vy": 0.0,
            "vtheta": 0.0
        },
        {
            "timestamp": 22.13243515586853,
            "x": 0.34496128745254495,
            "y": -0.28931686896320236,
            "theta": -23.955915046728144,
            "vx": 0.10349296192351803,
            "vy": -0.06397337328570789,
            "vtheta": 141.48119214806115
        },
        {
            "timestamp": 22.228902412414552,
            "x": 0.34496128745254495,
            "y": -0.28931686896320236,
            "theta": -23.955915046728144,
            "vx": 0.0,
            "vy": 0.0,
            "vtheta": 0.0
        },
        {
            "timestamp": 22.360780550003053,
            "x": 0.34496128745254495,
            "y": -0.28931686896320236,
            "theta": -23.955915046728144,
            "vx": 0.0,
            "vy": 0.0,
            "vtheta": 0.0
        },
        {
            "timestamp": 22.481120897293092,
            "x": 0.3377148688695468,
            "y": -0.27579172208989056,
            "theta": -36.24255376510987,
            "vx": -0.06021603515513483,
            "vy": 0.11239079143351714,
            "vtheta": -102.0990797772006
        },
        {
            "timestamp": 22.60159189796448,
            "x": 0.3377148688695468,
            "y": -0.27579172208989056,
            "theta": -36.24255376510987,
            "vx": 0.0,
            "vy": 0.0,
            "vtheta": 0.0
        },
        {
            "timestamp": 22.707966638565065,
            "x": 0.3377148688695468,
            "y": -0.27579172208989056,
            "theta": -36.24255376510987,
            "vx": 0.0,
            "vy": 0.0,
            "vtheta": 0.0
        },
        {
            "timestamp": 22.83219344711304,
            "x": 0.3377148688695468,
            "y": -0.27579172208989056,
            "theta": -36.24255376510987,
            "vx": 0.0,
            "vy": 0.0,
            "vtheta": 0.0
        },
        {
            "timestamp": 22.961495233535768,
            "x": 0.3377148688695468,
            "y": -0.27579172208989056,
            "theta": -36.24255376510987,
            "vx": 0.0,
            "vy": 0.0,
            "vtheta": 0.0
        },
        {
            "timestamp": 23.063657594680787,
            "x": 0.3377148688695468,
            "y": -0.27579172208989056,
            "theta": -36.24255376510987,
            "vx": 0.0,
            "vy": 0.0,
            "vtheta": 0.0
        },
        {
            "timestamp": 23.20734937286377,
            "x": 0.3377148688695468,
            "y": -0.27579172208989056,
            "theta": -36.24255376510987,
            "vx": 0.0,
            "vy": 0.0,
            "vtheta": 0.0
        },
        {
            "timestamp": 23.32110841369629,
            "x": 0.3377148688695468,
            "y": -0.27579172208989056,
            "theta": -36.24255376510987,
            "vx": 0.0,
            "vy": 0.0,
            "vtheta": 0.0
        },
        {
            "timestamp": 23.452221466064454,
            "x": 0.3435541875888608,
            "y": -0.28273758889470413,
            "theta": -31.476243299293127,
            "vx": 0.04453651725624718,
            "vy": -0.05297616583061198,
            "vtheta": 36.35267717231532
        },
        {
            "timestamp": 23.602300954818727,
            "x": 0.3677001761938641,
            "y": -0.2847474472677672,
            "theta": -14.293387668400799,
            "vx": 0.16088799878934748,
            "vy": -0.013391959086120217,
            "vtheta": 114.49169885583825
        },
        {
            "timestamp": 23.720363927841188,
            "x": 0.3882090879965214,
            "y": -0.28169850858213014,
            "theta": 8.81202830031094,
            "vx": 0.17371163267890574,
            "vy": 0.025824681587994582,
            "vtheta": 195.70416852298
        },
        {
            "timestamp": 23.821568323135377,
            "x": 0.3882090879965214,
            "y": -0.28169850858213014,
            "theta": 8.81202830031094,
            "vx": 0.0,
            "vy": 0.0,
            "vtheta": 0.0
        },
        {
            "timestamp": 23.935232950210573,
            "x": 0.37495388308074473,
            "y": -0.2789805202491822,
            "theta": -4.289131457224525,
            "vx": -0.1166167985314165,
            "vy": 0.023912349891843262,
            "vtheta": -115.26153821688378
        },
        {
            "timestamp": 24.04908044433594,
            "x": 0.33409362830623496,
            "y": -0.2690328232046804,
            "theta": -45.199346527129684,
            "vx": -0.3589034180191565,
            "vy": 0.08737739131568058,
            "vtheta": -359.3422532853976
        },
        {
            "timestamp": 24.18588383293152,
            "x": 0.31756401490447816,
            "y": -0.253051298824459,
            "theta": -75.74500063947201,
            "vx": -0.12082751437262808,
            "vy": 0.11682111491745359,
            "vtheta": -223.28141448777677
        },
        {
            "timestamp": 24.307159257888795,
            "x": 0.31188716413256967,
            "y": -0.21576723115093263,
            "theta": -120.17514136129763,
            "vx": -0.04680957229305453,
            "vy": 0.3074329996094535,
            "vtheta": -366.3573286795581
        },
        {
            "timestamp": 24.43974526023865,
            "x": 0.3202640437611765,
            "y": -0.20406542224353508,
            "theta": -141.04141675121895,
            "vx": 0.06318072405941344,
            "vy": 0.08825825275672837,
            "vtheta": -157.3791729149632
        },
        {
            "timestamp": 24.574227167129518,
            "x": 0.37005100215999315,
            "y": -0.17144488724071263,
            "theta": 161.8897805744463,
            "vx": 0.370213060997256,
            "vy": 0.2425644888371022,
            "vtheta": 2252.5795798797767
        },
        {
            "timestamp": 24.703702522277833,
            "x": 0.39448211646854187,
            "y": -0.1805222083533679,
            "theta": 128.4390803451702,
            "vx": 0.18869316311635223,
            "vy": -0.07010848591422748,
            "vtheta": -258.3557325713295
        },
        {
            "timestamp": 24.837251735687257,
            "x": 0.4164961756086433,
            "y": -0.18921319061130526,
            "theta": 98.5367129445492,
            "vx": 0.1648385533549541,
            "vy": -0.06507700072551739,
            "vtheta": -223.9052304183093
        },
        {
            "timestamp": 24.95128328895569,
            "x": 0.4250482473745908,
            "y": -0.23546403425403561,
            "theta": 47.150711136838595,
            "vx": 0.07499741537165344,
            "vy": -0.4055968924132334,
            "vtheta": -450.62967516321464
        },
        {
            "timestamp": 25.086466623306276,
            "x": 0.40550104237034895,
            "y": -0.26593584214363236,
            "theta": 1.2292714536568263,
            "vx": -0.1445977427479922,
            "vy": -0.2254109801032931,
            "vtheta": -339.6974923261517
        },
        {
            "timestamp": 25.20332677459717,
            "x": 0.3846452349659476,
            "y": -0.2750624280387547,
            "theta": -43.17895453096347,
            "vx": -0.17846808492046304,
            "vy": -0.07809835768913238,
            "vtheta": -380.01171052805967
        },
        {
            "timestamp": 25.346771312713624,
            "x": 0.3402762667950899,
            "y": -0.24721104096490262,
            "theta": -112.12142668573729,
            "vx": -0.3093109626442304,
            "vy": 0.1941613632666933,
            "vtheta": -480.6211031806805
        },
        {
            "timestamp": 25.455966306686403,
            "x": 0.342798278131907,
            "y": -0.21906984467034324,
            "theta": -165.34679713849948,
            "vx": 0.02309640071454048,
            "vy": 0.25771507713599784,
            "vtheta": -487.43416265063365
        },
        {
            "timestamp": 25.582996202468873,
            "x": 0.3559842452396729,
            "y": -0.20185972885622097,
            "theta": 165.9395812337951,
            "vx": 0.10380207766481932,
            "vy": 0.1354808307769796,
            "vtheta": 2607.9402516364967
        },
        {
            "timestamp": 25.751434637069703,
            "x": 0.351328095415587,
            "y": -0.19978320346604556,
            "theta": 172.3888469142678,
            "vx": -0.027643036668680624,
            "vy": 0.012328097177443029,
            "vtheta": 38.28856338968194
        },
        {
            "timestamp": 25.88322146034241,
            "x": 0.351328095415587,
            "y": -0.19978320346604556,
            "theta": 172.3888469142678,
            "vx": 0.0,
            "vy": 0.0,
            "vtheta": 0.0
        },
        {
            "timestamp": 26.03003151512146,
            "x": 0.3451814649848077,
            "y": -0.20063052423867994,
            "theta": 179.41314340023254,
            "vx": -0.04186791184043861,
            "vy": -0.005771544557418718,
            "vtheta": 47.846153974509654
        },
        {
            "timestamp": 26.14203364944458,
            "x": 0.3451814649848077,
            "y": -0.20063052423867994,
            "theta": 179.41314340023254,
            "vx": 0.0,
            "vy": 0.0,
            "vtheta": 0.0
        },
        {
            "timestamp": 26.272321773529054,
            "x": 0.3368202019359008,
            "y": -0.20123536818457355,
            "theta": -178.4160340530294,
            "vx": -0.06417517412013576,
            "vy": -0.004642356700918152,
            "vtheta": -2746.445080606598
        },
        {
            "timestamp": 26.3838341960907,
            "x": 0.3349786067264742,
            "y": -0.20258534648998552,
            "theta": -179.49110759062043,
            "vx": -0.016514709008393243,
            "vy": -0.012106079972082838,
            "vtheta": -9.640841019274992
        },
        {
            "timestamp": 26.519243551254274,
            "x": 0.339002009669641,
            "y": -0.2014823699631092,
            "theta": -177.1413688408662,
            "vx": 0.029712887549804175,
            "vy": 0.008145497226125422,
            "vtheta": 17.35285384762196
        },
        {
            "timestamp": 26.637406421661378,
            "x": 0.33463486312315793,
            "y": -0.20098796665367621,
            "theta": -172.80003555289878,
            "vx": -0.036958703960364325,
            "vy": 0.004184083441182703,
            "vtheta": 36.7402490563262
        },
        {
            "timestamp": 26.728609157562257,
            "x": 0.3231606415165326,
            "y": -0.20752710390188125,
            "theta": -169.62744220455428,
            "vx": -0.12581005924093924,
            "vy": -0.07169891542850113,
            "vtheta": 34.78616421981611
        },
        {
            "timestamp": 26.86696441268921,
            "x": 0.3087816274785795,
            "y": -0.2217889985580231,
            "theta": -156.09373445117063,
            "vx": -0.10392821020610382,
            "vy": -0.10308169821995766,
            "vtheta": 97.81853057164533
        },
        {
            "timestamp": 27.021833492279054,
            "x": 0.3066880346651427,
            "y": -0.23274362477487706,
            "theta": -135.0920596737179,
            "vx": -0.013518468754263149,
            "vy": -0.07073475380538372,
            "vtheta": 135.6092180122314
        },
        {
            "timestamp": 27.14369542694092,
            "x": 0.2960983017562682,
            "y": -0.2673216200642428,
            "theta": -98.2285836185225,
            "vx": -0.08689943203559186,
            "vy": -0.28374730292367817,
            "vtheta": 302.50197617067073
        },
        {
            "timestamp": 27.28132994270325,
            "x": 0.29989933431384524,
            "y": -0.28567416579796834,
            "theta": -76.09323948885796,
            "vx": 0.027616855674057406,
            "vy": -0.13334261127795285,
            "vtheta": 160.82698447450812
        },
        {
            "timestamp": 27.414126707077028,
            "x": 0.31830069346243267,
            "y": -0.3200937543902727,
            "theta": -46.2597194247984,
            "vx": 0.13856782757743735,
            "vy": -0.25918996411256323,
            "vtheta": 224.6554741355595
        },
        {
            "timestamp": 27.546220136642457,
            "x": 0.33592013860925796,
            "y": -0.3295631791653535,
            "theta": -15.055285078266223,
            "vx": 0.13338623430999547,
            "vy": -0.07168732620716992,
            "vtheta": 236.23002634719026
        },
        {
            "timestamp": 27.650869918823243,
            "x": 0.376253779947394,
            "y": -0.3240766556959806,
            "theta": 11.944173467658134,
            "vx": 0.3854154351555007,
            "vy": 0.052427471467592114,
            "vtheta": 257.9982297457806
        },
        {
            "timestamp": 27.791451288223268,
            "x": 0.4034928395709399,
            "y": -0.29404842308628854,
            "theta": 38.93430077710365,
            "vx": 0.19376009594868238,
            "vy": 0.2136003706454637,
            "vtheta": 191.9893612121894
        },
        {
            "timestamp": 27.930716110229493,
            "x": 0.41942428951528943,
            "y": -0.264109591705235,
            "theta": 76.05789130591464,
            "vx": 0.11439679967161659,
            "vy": 0.21497770183280857,
            "vtheta": 266.56832640156205
        },
        {
            "timestamp": 28.04994781112671,
            "x": 0.4170931133784319,
            "y": -0.2270076733527008,
            "theta": 110.63097394197658,
            "vx": -0.01955164708140075,
            "vy": 0.31117494821715047,
            "vtheta": 289.9655240670057
        },
        {
            "timestamp": 28.206742359161378,
            "x": 0.4018302930483983,
            "y": -0.21315829087525098,
            "theta": 128.42280334748102,
            "vx": -0.09734279999747787,
            "vy": 0.08832821453962585,
            "vtheta": 113.47224523119638
        },
        {
            "timestamp": 28.360002590179445,
            "x": 0.4018302930483983,
            "y": -0.21315829087525098,
            "theta": 128.42280334748102,
            "vx": 0.0,
            "vy": 0.0,
            "vtheta": 0.0
        },
        {
            "timestamp": 28.457874132156373,
            "x": 0.4018302930483983,
            "y": -0.21315829087525098,
            "theta": 128.42280334748102,
            "vx": 0.0,
            "vy": 0.0,
            "vtheta": 0.0
        },
        {
            "timestamp": 28.579620672225953,
            "x": 0.4018302930483983,
            "y": -0.21315829087525098,
            "theta": 128.42280334748102,
            "vx": 0.0,
            "vy": 0.0,
            "vtheta": 0.0
        },
        {
            "timestamp": 28.714791370391847,
            "x": 0.4018302930483983,
            "y": -0.21315829087525098,
            "theta": 128.42280334748102,
            "vx": 0.0,
            "vy": 0.0,
            "vtheta": 0.0
        },
        {
            "timestamp": 28.84349472618103,
            "x": 0.404580650266286,
            "y": -0.2073893169849526,
            "theta": 123.06482006590102,
            "vx": 0.021369739747833457,
            "vy": 0.04482380319397361,
            "vtheta": -41.630486235000376
        },
        {
            "timestamp": 28.946861577987672,
            "x": 0.404580650266286,
            "y": -0.2073893169849526,
            "theta": 123.06482006590102,
            "vx": 0.0,
            "vy": 0.0,
            "vtheta": 0.0
        },
        {
            "timestamp": 29.08013947105408,
            "x": 0.404580650266286,
            "y": -0.2073893169849526,
            "theta": 123.06482006590102,
            "vx": 0.0,
            "vy": 0.0,
            "vtheta": 0.0
        },
        {
            "timestamp": 29.187940908432008,
            "x": 0.404580650266286,
            "y": -0.2073893169849526,
            "theta": 123.06482006590102,
            "vx": 0.0,
            "vy": 0.0,
            "vtheta": 0.0
        },
        {
            "timestamp": 29.30161674118042,
            "x": 0.404580650266286,
            "y": -0.2073893169849526,
            "theta": 123.06482006590102,
            "vx": 0.0,
            "vy": 0.0,
            "vtheta": 0.0
        },
        {
            "timestamp": 29.39888031578064,
            "x": 0.3906748983543313,
            "y": -0.19971760924296258,
            "theta": 150.07150073392094,
            "vx": -0.14296978050736053,
            "vy": 0.07887544513475751,
            "vtheta": 277.66489951685276
        },
        {
            "timestamp": 29.54308493232727,
            "x": 0.36034673573853565,
            "y": -0.1931242030148811,
            "theta": 172.12124532083078,
            "vx": -0.21031339593756027,
            "vy": 0.04572257383971762,
            "vtheta": 152.90595485047945
        },
        {
            "timestamp": 29.700649810791017,
            "x": 0.3444922397488263,
            "y": -0.19745194418758505,
            "theta": -173.90668563294085,
            "vx": -0.10062201770020328,
            "vy": -0.027466407583335583,
            "vtheta": -2196.0981046508464
        },
        {
            "timestamp": 29.8406315574646,
            "x": 0.3129148254220599,
            "y": -0.22063319939754744,
            "theta": -134.35688434957666,
            "vx": -0.2255823711101428,
            "vy": -0.1656019856933028,
            "vtheta": 282.5354178183551
        },
        {
            "timestamp": 29.95190699195862,
            "x": 0.29687954886100665,
            "y": -0.24950006821327148,
            "theta": -94.99190337329314,
            "vx": -0.14410437158899791,
            "vy": -0.25941816311016724,
            "vtheta": 353.7616469913629
        },
        {
            "timestamp": 30.098482681274415,
            "x": 0.30114858264763095,
            "y": -0.2808477898919025,
            "theta": -73.63523906393127,
            "vx": 0.029125114857394305,
            "vy": -0.2138671277956106,
            "vtheta": 145.7040005000362
        },
        {
            "timestamp": 30.21323258972168,
            "x": 0.3181179005242993,
            "y": -0.30849668768212657,
            "theta": -50.447264251900094,
            "vx": 0.14788088379579614,
            "vy": -0.24094919259068834,
            "vtheta": 202.0740157948572
        },
        {
            "timestamp": 30.33429200744629,
            "x": 0.33450391349522746,
            "y": -0.3228573642189237,
            "theta": -35.11119846767456,
            "vx": 0.13535512791085538,
            "vy": -0.11862502568338254,
            "vtheta": 126.6821373543412
        },
        {
            "timestamp": 30.48251969909668,
            "x": 0.3278781786657222,
            "y": -0.31250070084798404,
            "theta": -42.805628258307394,
            "vx": -0.04469970999165712,
            "vy": 0.06986996326817832,
            "vtheta": -51.909529892571555
        },
        {
            "timestamp": 30.602735830307008,
            "x": 0.3151440934613171,
            "y": -0.3049775975055942,
            "theta": -49.687183729774,
            "vx": -0.10592659301376012,
            "vy": 0.06257981575889827,
            "vtheta": -57.24319525327934
        },
        {
            "timestamp": 30.736366582870485,
            "x": 0.30610585264586054,
            "y": -0.2616957543580083,
            "theta": -97.73907436074117,
            "vx": -0.06763593440935887,
            "vy": 0.32389133726554764,
            "vtheta": -359.58706891321157
        },
        {
            "timestamp": 30.883947444915773,
            "x": 0.3046327455074373,
            "y": -0.22294918356845136,
            "theta": -146.5777972862236,
            "vx": -0.009981694902765879,
            "vy": 0.2625446839961321,
            "vtheta": -330.9285651854732
        },
        {
            "timestamp": 30.978506399154664,
            "x": 0.3354458782624212,
            "y": -0.19485863816996135,
            "theta": 172.97949625624386,
            "vx": 0.3258616066875944,
            "vy": 0.29706912078916076,
            "vtheta": 3379.4503769060852
        },
        {
            "timestamp": 31.10028822517395,
            "x": 0.37770643735682513,
            "y": -0.196685181506439,
            "theta": 109.62554932766506,
            "vx": 0.3470186026584206,
            "vy": -0.014998488659452025,
            "vtheta": -520.2249711590396
        },
        {
            "timestamp": 31.244104219436647,
            "x": 0.3955834460140044,
            "y": -0.22164073043894797,
            "theta": 71.29810487917743,
            "vx": 0.12430473222974778,
            "vy": -0.17352415536567511,
            "vtheta": -266.50335134824047
        },
        {
            "timestamp": 31.391969038009645,
            "x": 0.39423317823354953,
            "y": -0.2617727270553703,
            "theta": 11.816231861540478,
            "vx": -0.009131771799985552,
            "vy": -0.27141004198108104,
            "vtheta": -402.27197782190416
        },
        {
            "timestamp": 31.505741191864015,
            "x": 0.3572059859670182,
            "y": -0.2758605140993998,
            "theta": -52.38181613864449,
            "vx": -0.325450393722234,
            "vy": -0.12382456134268212,
            "vtheta": -564.2685474897428
        },
        {
            "timestamp": 31.649677349090577,
            "x": 0.3325662799923341,
            "y": -0.27212216421618013,
            "theta": -90.14677233931067,
            "vx": -0.17118496456661667,
            "vy": 0.025972277954700078,
            "vtheta": -262.37296401641674
        },
        {
            "timestamp": 31.790932727813722,
            "x": 0.32894182797155697,
            "y": -0.26535619416621825,
            "theta": -101.255735804452,
            "vx": -0.025658860239799814,
            "vy": 0.04789884895797799,
            "vtheta": -78.64453421568108
        },
        {
            "timestamp": 31.922679735183717,
            "x": 0.3270575849514221,
            "y": -0.2668002103528034,
            "theta": -96.29763882668622,
            "vx": -0.014301979663516632,
            "vy": -0.010960523623354786,
            "vtheta": 37.63346945590633
        },
        {
            "timestamp": 32.0621310005188,
            "x": 0.3270575849514221,
            "y": -0.2668002103528034,
            "theta": -96.29763882668622,
            "vx": 0.0,
            "vy": 0.0,
            "vtheta": 0.0
        },
        {
            "timestamp": 32.182888103485105,
            "x": 0.3323497668493021,
            "y": -0.2608406648557347,
            "theta": -99.58380476290787,
            "vx": 0.0438250154059801,
            "vy": 0.04935151101406761,
            "vtheta": -27.21302395883491
        },
        {
            "timestamp": 32.307858777999876,
            "x": 0.3251692829889348,
            "y": -0.2682473371670488,
            "theta": -95.95975677085598,
            "vx": -0.05745735060042921,
            "vy": -0.05926728282512935,
            "vtheta": 28.999187258316084
        },
        {
            "timestamp": 32.44282443618774,
            "x": 0.32536815737387415,
            "y": -0.27959962973972513,
            "theta": -82.76209355113045,
            "vx": 0.0014735184313515804,
            "vy": -0.08411245293876497,
            "vtheta": 97.78534330084891
        },
        {
            "timestamp": 32.57581074333191,
            "x": 0.33230060739120537,
            "y": -0.2915471239626133,
            "theta": -75.7576940794523,
            "vx": 0.05212905122492077,
            "vy": -0.08984003300382169,
            "vtheta": 52.67008026687257
        },
        {
            "timestamp": 32.70411379432678,
            "x": 0.3435866112126811,
            "y": -0.31362811996077533,
            "theta": -45.97169685903147,
            "vx": 0.08796364337373938,
            "vy": -0.17210031894755484,
            "vtheta": 232.15346002653575
        },
        {
            "timestamp": 32.8541322479248,
            "x": 0.3598260128662243,
            "y": -0.3180514822065859,
            "theta": -33.865991275935016,
            "vx": 0.10824936042239855,
            "vy": -0.029485454220605892,
            "vtheta": 80.69477649419011
        },
        {
            "timestamp": 32.92226154899597,
            "x": 0.3809686845311297,
            "y": -0.3260223510446052,
            "theta": -7.812954816112495,
            "vx": 0.31033155092579107,
            "vy": -0.1169961927202661,
            "vtheta": 382.4057498051808
        },
        {
            "timestamp": 33.011020732879636,
            "x": 0.4138612869507111,
            "y": -0.32186393430321203,
            "theta": 20.019001427879285,
            "vx": 0.37058252431311667,
            "vy": 0.04685055179014977,
            "vtheta": 313.567058936346
        },
        {
            "timestamp": 33.21999151802063,
            "x": 0.4335761271043657,
            "y": -0.2996121859398679,
            "theta": 43.454986975643195,
            "vx": 0.0943425663082671,
            "vy": 0.10648258008090002,
            "vtheta": 112.14957886075705
        },
        {
            "timestamp": 33.32863338088989,
            "x": 0.446197636055827,
            "y": -0.292834416633614,
            "theta": 59.352864416171556,
            "vx": 0.11617537308477265,
            "vy": 0.06238635022680091,
            "vtheta": 146.33288697985168
        },
        {
            "timestamp": 33.444747520446775,
            "x": 0.446197636055827,
            "y": -0.292834416633614,
            "theta": 59.352864416171556,
            "vx": 0.0,
            "vy": 0.0,
            "vtheta": 0.0
        },
        {
            "timestamp": 33.57178671455383,
            "x": 0.446197636055827,
            "y": -0.292834416633614,
            "theta": 59.352864416171556,
            "vx": 0.0,
            "vy": 0.0,
            "vtheta": 0.0
        },
        {
            "timestamp": 33.71027119255066,
            "x": 0.446197636055827,
            "y": -0.292834416633614,
            "theta": 59.352864416171556,
            "vx": 0.0,
            "vy": 0.0,
            "vtheta": 0.0
        },
        {
            "timestamp": 33.835402084350584,
            "x": 0.443420762546491,
            "y": -0.2894967657310779,
            "theta": 54.300289998147385,
            "vx": -0.022191750329534982,
            "vy": 0.02667327671469552,
            "vtheta": -40.378313822799186
        },
        {
            "timestamp": 33.93828685379028,
            "x": 0.443420762546491,
            "y": -0.2894967657310779,
            "theta": 50.45822162004844,
            "vx": 0.0,
            "vy": 0.0,
            "vtheta": -37.3434124314275
        },
        {
            "timestamp": 34.051816535949705,
            "x": 0.443420762546491,
            "y": -0.2894967657310779,
            "theta": 50.45822162004844,
            "vx": 0.0,
            "vy": 0.0,
            "vtheta": 0.0
        },
        {
            "timestamp": 34.18479926681518,
            "x": 0.4445086767302632,
            "y": -0.2942500572912511,
            "theta": 51.77529794344282,
            "vx": 0.008180868122438317,
            "vy": -0.03574367535722718,
            "vtheta": 9.904115480428041
        },
        {
            "timestamp": 34.301538063049314,
            "x": 0.4441458634847335,
            "y": -0.29266486135978953,
            "theta": 55.687096895700634,
            "vx": -0.0031079063450509866,
            "vy": 0.013578998435809597,
            "vtheta": 33.508988257959444
        },
        {
            "timestamp": 34.47956760025024,
            "x": 0.4481145224637042,
            "y": -0.28369934223787674,
            "theta": 58.90563920279621,
            "vx": 0.022292137818072218,
            "vy": 0.050359728294940884,
            "vtheta": 18.078698387352787
        },
        {
            "timestamp": 34.63113195991516,
            "x": 0.4490686285521421,
            "y": -0.27915247390833503,
            "theta": 61.787485921779535,
            "vx": 0.00629505571459705,
            "vy": 0.029999587895162563,
            "vtheta": 19.01401309222431
        },
        {
            "timestamp": 34.738681865692136,
            "x": 0.4490686285521421,
            "y": -0.27915247390833503,
            "theta": 61.787485921779535,
            "vx": 0.0,
            "vy": 0.0,
            "vtheta": 0.0
        },
        {
            "timestamp": 34.866309238433836,
            "x": 0.452053053944549,
            "y": -0.2748018835519891,
            "theta": 67.8666765747047,
            "vx": 0.023383897421809165,
            "vy": 0.03408822310517161,
            "vtheta": 47.63234188976556
        },
        {
            "timestamp": 34.97954709625244,
            "x": 0.452053053944549,
            "y": -0.2748018835519891,
            "theta": 67.8666765747047,
            "vx": 0.0,
            "vy": 0.0,
            "vtheta": 0.0
        },
        {
            "timestamp": 35.1019681224823,
            "x": 0.452053053944549,
            "y": -0.2748018835519891,
            "theta": 67.8666765747047,
            "vx": 0.0,
            "vy": 0.0,
            "vtheta": 0.0
        },
        {
            "timestamp": 35.208682371139524,
            "x": 0.452053053944549,
            "y": -0.2748018835519891,
            "theta": 67.8666765747047,
            "vx": 0.0,
            "vy": 0.0,
            "vtheta": 0.0
        },
        {
            "timestamp": 35.31209356880188,
            "x": 0.452053053944549,
            "y": -0.2748018835519891,
            "theta": 67.8666765747047,
            "vx": 0.0,
            "vy": 0.0,
            "vtheta": 0.0
        },
        {
            "timestamp": 35.46589310264587,
            "x": 0.452053053944549,
            "y": -0.2748018835519891,
            "theta": 67.8666765747047,
            "vx": 0.0,
            "vy": 0.0,
            "vtheta": 0.0
        },
        {
            "timestamp": 35.578205181121824,
            "x": 0.452053053944549,
            "y": -0.2748018835519891,
            "theta": 67.8666765747047,
            "vx": 0.0,
            "vy": 0.0,
            "vtheta": 0.0
        },
        {
            "timestamp": 35.7274723777771,
            "x": 0.452053053944549,
            "y": -0.2748018835519891,
            "theta": 67.8666765747047,
            "vx": 0.0,
            "vy": 0.0,
            "vtheta": 0.0
        },
        {
            "timestamp": 35.86308868026733,
            "x": 0.452053053944549,
            "y": -0.2748018835519891,
            "theta": 67.8666765747047,
            "vx": 0.0,
            "vy": 0.0,
            "vtheta": 0.0
        },
        {
            "timestamp": 35.97884423828125,
            "x": 0.452053053944549,
            "y": -0.2748018835519891,
            "theta": 67.8666765747047,
            "vx": 0.0,
            "vy": 0.0,
            "vtheta": 0.0
        },
        {
            "timestamp": 36.10494692420959,
            "x": 0.45169127321824487,
            "y": -0.27323375917698267,
            "theta": 74.16569745220318,
            "vx": -0.002868937514222978,
            "vy": 0.01243529718230961,
            "vtheta": 49.9515203116115
        },
        {
            "timestamp": 36.243204427719114,
            "x": 0.45169127321824487,
            "y": -0.27323375917698267,
            "theta": 74.16569745220318,
            "vx": 0.0,
            "vy": 0.0,
            "vtheta": 0.0
        },
        {
            "timestamp": 36.36137993431091,
            "x": 0.45169127321824487,
            "y": -0.27323375917698267,
            "theta": 74.16569745220318,
            "vx": 0.0,
            "vy": 0.0,
            "vtheta": 0.0
        },
        {
            "timestamp": 36.48231799697876,
            "x": 0.45169127321824487,
            "y": -0.27323375917698267,
            "theta": 74.16569745220318,
            "vx": 0.0,
            "vy": 0.0,
            "vtheta": 0.0
        },
        {
            "timestamp": 36.626103950500486,
            "x": 0.45169127321824487,
            "y": -0.27323375917698267,
            "theta": 74.16569745220318,
            "vx": 0.0,
            "vy": 0.0,
            "vtheta": 0.0
        },
        {
            "timestamp": 36.758987976074216,
            "x": 0.44628529600721845,
            "y": -0.2498017628903344,
            "theta": 93.31396778868726,
            "vx": -0.0406819193479876,
            "vy": 0.17633418453030736,
            "vtheta": 144.0976088270272
        },
        {
            "timestamp": 36.86603171920776,
            "x": 0.44899389354686975,
            "y": -0.22740926659321445,
            "theta": 107.38695840405116,
            "vx": 0.025303651202407306,
            "vy": 0.20919014639822217,
            "vtheta": 131.46953015092907
        },
        {
            "timestamp": 36.99327666854858,
            "x": 0.4545169234463313,
            "y": -0.21753994874162746,
            "theta": 119.89072440253717,
            "vx": 0.04340470822671608,
            "vy": 0.07756156847650138,
            "vtheta": 98.26532261799404
        },
        {
            "timestamp": 37.128404689788816,
            "x": 0.4496677430627234,
            "y": -0.2050802448400813,
            "theta": 146.18717237195762,
            "vx": -0.03588582396975179,
            "vy": 0.09220666289040783,
            "vtheta": 194.6039594753621
        },
        {
            "timestamp": 37.23947222328186,
            "x": 0.43179792283911334,
            "y": -0.1955327147493067,
            "theta": 152.46035869695072,
            "vx": -0.16089148342102635,
            "vy": 0.0859614847877461,
            "vtheta": 56.480828624740276
        },
        {
            "timestamp": 37.34246952629089,
            "x": 0.42492776827567974,
            "y": -0.18279735704029576,
            "theta": 170.86604630883843,
            "vx": -0.06670227629971107,
            "vy": 0.1236474872346318,
            "vtheta": 178.70067539800993
        },
        {
            "timestamp": 37.4914568195343,
            "x": 0.4259821956723538,
            "y": -0.1873859172461959,
            "theta": 162.01884779960724,
            "vx": 0.0070772974910778405,
            "vy": -0.030798332569231812,
            "vtheta": -59.38223533450647
        },
        {
            "timestamp": 37.62568838691711,
            "x": 0.422897192724909,
            "y": -0.18254539218433544,
            "theta": 164.13423863521865,
            "vx": -0.02298269332314902,
            "vy": 0.03606100380289735,
            "vtheta": 15.75926495426045
        },
        {
            "timestamp": 37.76579029655456,
            "x": 0.422897192724909,
            "y": -0.18254539218433544,
            "theta": 164.13423863521865,
            "vx": 0.0,
            "vy": 0.0,
            "vtheta": 0.0
        },
        {
            "timestamp": 37.8732243309021,
            "x": 0.42457662547847363,
            "y": -0.18126928609778248,
            "theta": 172.4691679031198,
            "vx": 0.015632222728710943,
            "vy": 0.011878043064313608,
            "vtheta": 77.58183259635217
        },
        {
            "timestamp": 37.97629101371765,
            "x": 0.42086345814610665,
            "y": -0.18229303533899915,
            "theta": 166.89052359010765,
            "vx": -0.03602684428111529,
            "vy": -0.009932882414085051,
            "vtheta": -54.12655341780715
        },
        {
            "timestamp": 38.1004758605957,
            "x": 0.42086345814610665,
            "y": -0.18229303533899915,
            "theta": 166.89052359010765,
            "vx": 0.0,
            "vy": 0.0,
            "vtheta": 0.0
        },
        {
            "timestamp": 38.23122150993347,
            "x": 0.4195280851384889,
            "y": -0.18510538673496993,
            "theta": 170.5914011986165,
            "vx": -0.010213517729893736,
            "vy": -0.021510095442681544,
            "vtheta": 28.30593314006184
        },
        {
            "timestamp": 38.33641321754455,
            "x": 0.4195280851384889,
            "y": -0.18510538673496993,
            "theta": 170.5914011986165,
            "vx": 0.0,
            "vy": 0.0,
            "vtheta": 0.0
        },
        {
            "timestamp": 38.45316369628906,
            "x": 0.4171369513689636,
            "y": -0.18332046236934985,
            "theta": 179.39418398317596,
            "vx": -0.02048071918195685,
            "vy": 0.015288368705760572,
            "vtheta": 75.3982585700844
        },
        {
            "timestamp": 38.57620771026611,
            "x": 0.41748758702699595,
            "y": -0.18485451186927407,
            "theta": 173.34152857269396,
            "vx": 0.0028496766864070018,
            "vy": -0.012467485823490297,
            "vtheta": -49.190978210536095
        },
        {
            "timestamp": 38.67875273323059,
            "x": 0.4243025957418809,
            "y": -0.18866944509862962,
            "theta": 165.95579719759812,
            "vx": 0.06645869802228936,
            "vy": -0.037202519625716794,
            "vtheta": -72.02427930270515
        },
        {
            "timestamp": 38.8138707408905,
            "x": 0.4375033635253603,
            "y": -0.19472868792137252,
            "theta": 140.63877784070246,
            "vx": 0.0976980641744313,
            "vy": -0.04484408057580173,
            "vtheta": -187.36969109711725
        },
        {
            "timestamp": 38.92734272575378,
            "x": 0.4612582817118474,
            "y": -0.2049545156765702,
            "theta": 117.3684551523993,
            "vx": 0.2093461061345552,
            "vy": -0.09011764240766958,
            "vtheta": -205.07548815983802
        },
        {
            "timestamp": 39.05357678031921,
            "x": 0.4675299178787903,
            "y": -0.22345419884915707,
            "theta": 90.24616536909846,
            "vx": 0.049682601010745134,
            "vy": -0.14655065335795037,
            "vtheta": -214.85715464556205
        },
        {
            "timestamp": 39.19316656684875,
            "x": 0.4689544487030488,
            "y": -0.24603037976629705,
            "theta": 72.7931454260385,
            "vx": 0.010205122163125165,
            "vy": -0.1617323264002717,
            "vtheta": -125.03078038138858
        },
        {
            "timestamp": 39.31128842926025,
            "x": 0.4689544487030488,
            "y": -0.24603037976629705,
            "theta": 72.7931454260385,
            "vx": 0.0,
            "vy": 0.0,
            "vtheta": 0.0
        },
        {
            "timestamp": 39.4416943321228,
            "x": 0.46277188243686157,
            "y": -0.2529498298228613,
            "theta": 62.95115266554998,
            "vx": -0.047410171859350744,
            "vy": -0.05306086538013179,
            "vtheta": -75.47198818800591
        },
        {
            "timestamp": 39.57168538665771,
            "x": 0.6742859820378003,
            "y": -0.5547209995663013,
            "theta": 175.3406608074283,
            "vx": 1.627143501202475,
            "vy": -2.3214764340756413,
            "vtheta": 864.5941718373667
        },
        {
            "timestamp": 39.689848495483396,
            "x": 0.7893541271245132,
            "y": -0.7692226335085217,
            "theta": -9.29848161562264,
            "vx": 0.9738076987840899,
            "vy": -1.8153012058836164,
            "vtheta": -1562.5785768334347
        },
        {
            "timestamp": 39.78676064109802,
            "x": 0.6648314757815004,
            "y": -0.7127267076537094,
            "theta": 67.77757446840106,
            "vx": -1.2849024294455662,
            "vy": 0.5829602213067411,
            "vtheta": 795.3188487903309
        },
        {
            "timestamp": 39.90914137458801,
            "x": 0.6503816724075983,
            "y": -0.7583532587736043,
            "theta": 26.108493523047404,
            "vx": -0.11807253447360644,
            "vy": -0.3728246254025498,
            "vtheta": -340.4872626356816
        },
        {
            "timestamp": 40.026126218795774,
            "x": 0.6754569037632581,
            "y": -0.8951404515649755,
            "theta": -4.8172463366669,
            "vx": 0.21434598238320943,
            "vy": -1.1692727696285066,
            "vtheta": -264.3568068081585
        },
        {
            "timestamp": 40.14935262298584,
            "x": 0.6804195640831179,
            "y": -0.9499080279608452,
            "theta": -24.049758128675244,
            "vx": 0.040272702530583,
            "vy": -0.4444467624925305,
            "vtheta": -156.0746003944436
        },
        {
            "timestamp": 40.289572549819944,
            "x": 0.6866296338778565,
            "y": -0.9584446537654355,
            "theta": -19.664477402028492,
            "vx": 0.04428806899953455,
            "vy": -0.06088026143880393,
            "vtheta": 31.27430477006993
        }
    ]
}